napari_nd2_folder_viewer/__init__.py
napari_nd2_folder_viewer/_version.py
napari_nd2_folder_viewer/_widget.py
napari_nd2_folder_viewer/exp_info.py
napari_nd2_folder_viewer/napari.yaml
napari_nd2_folder_viewer/_tests/__init__.py
napari_nd2_folder_viewer/_tests/test_widget.py
napari_nd2_folder_viewer-0.0.13.dist-info/LICENSE
napari_nd2_folder_viewer-0.0.13.dist-info/METADATA
napari_nd2_folder_viewer-0.0.13.dist-info/WHEEL
napari_nd2_folder_viewer-0.0.13.dist-info/entry_points.txt
napari_nd2_folder_viewer-0.0.13.dist-info/top_level.txt
napari_nd2_folder_viewer-0.0.13.dist-info/RECORD
