Metadata-Version: 2.1
Name: napari-nd2-folder-viewer
Version: 0.0.13
Summary: Look through separate nd2 files in one viewer.
Home-page: https://github.com/gatoniel/napari-nd2-folder-viewer
Author: Niklas Netter
Author-email: niknett@gmail.com
License: BSD-3-Clause
Project-URL: Bug Tracker, https://github.com/gatoniel/napari-nd2-folder-viewer/issues
Project-URL: Documentation, https://github.com/gatoniel/napari-nd2-folder-viewer#README.md
Project-URL: Source Code, https://github.com/gatoniel/napari-nd2-folder-viewer
Project-URL: User Support, https://github.com/gatoniel/napari-nd2-folder-viewer/issues
Classifier: Development Status :: 2 - Pre-Alpha
Classifier: Framework :: napari
Classifier: Intended Audience :: Developers
Classifier: License :: OSI Approved :: BSD License
Classifier: Operating System :: OS Independent
Classifier: Programming Language :: Python
Classifier: Programming Language :: Python :: 3
Classifier: Programming Language :: Python :: 3 :: Only
Classifier: Programming Language :: Python :: 3.8
Classifier: Programming Language :: Python :: 3.9
Classifier: Programming Language :: Python :: 3.10
Classifier: Topic :: Scientific/Engineering :: Image Processing
Requires-Python: >=3.8
License-File: LICENSE
Requires-Dist: numpy
Requires-Dist: magicgui
Requires-Dist: qtpy
Requires-Dist: pyyaml
Requires-Dist: marshmallow
Requires-Dist: desert
Requires-Dist: nd2 (>=0.4.3)
Requires-Dist: dask
Requires-Dist: pandas
Requires-Dist: openpyxl
Requires-Dist: julian
Requires-Dist: napari-animation
Requires-Dist: scikit-learn
Provides-Extra: testing
Requires-Dist: tox ; extra == 'testing'
Requires-Dist: pytest ; extra == 'testing'
Requires-Dist: pytest-cov ; extra == 'testing'
Requires-Dist: pytest-qt ; extra == 'testing'
Requires-Dist: napari ; extra == 'testing'
Requires-Dist: pyqt5 ; extra == 'testing'
